patchify/__init__.py
patchify/tests/__init__.py
patchify/tests/test_sanity.py
patchify-0.2.2.dist-info/LICENSE
patchify-0.2.2.dist-info/WHEEL
patchify-0.2.2.dist-info/METADATA
patchify-0.2.2.dist-info/RECORD
