Metadata-Version: 2.1
Name: patchify
Version: 0.2.2
Summary: A library that helps you split image into small, overlappable patches, and merge patches back into the original image.
Home-page: https://github.com/dovahcrow/patchify.py
License: MIT
Keywords: patch,image,split
Author: Weiyuan Wu
Author-email: doomsplayer@gmail.com
Requires-Python: >=3.6,<4.0
Classifier: Development Status :: 4 - Beta
Classifier: Intended Audience :: Developers
Classifier: License :: OSI Approved :: MIT License
Classifier: Programming Language :: Python :: 3
Classifier: Programming Language :: Python :: 3.6
Classifier: Programming Language :: Python :: 3.7
Classifier: Programming Language :: Python :: 3.8
Classifier: Topic :: Multimedia :: Graphics :: Editors
Requires-Dist: scikit-image (>=0.17.2,<0.18.0)
Project-URL: Repository, https://github.com/dovahcrow/patchify.py
